LICENSE
MANIFEST.in
README.md
distributed_wellbeing.py
peers.txt
sentiment_tweets.py
setup.py
distributed_wellbeing.egg-info/PKG-INFO
distributed_wellbeing.egg-info/SOURCES.txt
distributed_wellbeing.egg-info/dependency_links.txt
distributed_wellbeing.egg-info/entry_points.txt
distributed_wellbeing.egg-info/requires.txt
distributed_wellbeing.egg-info/top_level.txt