Metadata-Version: 1.0
Name: distributed-wellbeing
Version: 2016.6.27.1010
Summary: prototype decentralised wellbeing analysis and distribution system
Home-page: https://github.com/wdbm/distributed_wellbeing
Author: Will Breaden Madden
Author-email: w.bm@cern.ch
License: GPLv3
Platform: UNKNOWN
